{"rows":[{"year":1962,"intra_dd":-26.0,"ret":-13.2},{"year":1963,"intra_dd":-4.4,"ret":39.4},{"year":1964,"intra_dd":-7.9,"ret":26.2},{"year":1965,"intra_dd":-12.5,"ret":25.8},{"year":1966,"intra_dd":-17.3,"ret":5.9},{"year":1967,"intra_dd":-10.8,"ret":50.8},{"year":1968,"intra_dd":-14.4,"ret":10.8},{"year":1969,"intra_dd":-13.8,"ret":15.1},{"year":1970,"intra_dd":-26.0,"ret":4.5},{"year":1971,"intra_dd":-8.5,"ret":49.1},{"year":1972,"intra_dd":-10.1,"ret":24.7},{"year":1973,"intra_dd":-21.6,"ret":-12.6},{"year":1974,"intra_dd":-63.0,"ret":-56.3},{"year":1975,"intra_dd":-24.4,"ret":53.8},{"year":1976,"intra_dd":-18.9,"ret":-2.3},{"year":1977,"intra_dd":-11.5,"ret":-1.2},{"year":1978,"intra_dd":-13.3,"ret":25.8},{"year":1979,"intra_dd":-28.2,"ret":-16.5},{"year":1980,"intra_dd":-19.9,"ret":5.7},{"year":1981,"intra_dd":-20.8,"ret":9.7},{"year":1982,"intra_dd":-16.0,"ret":60.6},{"year":1983,"intra_dd":-17.8,"ret":10.5},{"year":1984,"intra_dd":-10.4,"ret":22.8},{"year":1985,"intra_dd":-8.4,"ret":42.4},{"year":1986,"intra_dd":-24.3,"ret":40.0},{"year":1987,"intra_dd":-41.2,"ret":2.6},{"year":1988,"intra_dd":-11.9,"ret":15.3},{"year":1989,"intra_dd":-9.4,"ret":81.6},{"year":1990,"intra_dd":-21.2,"ret":21.5},{"year":1991,"intra_dd":-9.1,"ret":80.2},{"year":1992,"intra_dd":-18.1,"ret":5.8},{"year":1993,"intra_dd":-12.8,"ret":8.0},{"year":1994,"intra_dd":-11.1,"ret":17.8},{"year":1995,"intra_dd":-10.1,"ret":45.5},{"year":1996,"intra_dd":-9.7,"ret":41.8},{"year":1997,"intra_dd":-25.3,"ret":29.7},{"year":1998,"intra_dd":-35.9,"ret":0.9},{"year":1999,"intra_dd":-32.2,"ret":-12.4},{"year":2000,"intra_dd":-35.0,"ret":9.5},{"year":2001,"intra_dd":-29.0,"ret":-20.7},{"year":2002,"intra_dd":-23.7,"ret":-6.1},{"year":2003,"intra_dd":-19.0,"ret":15.5},{"year":2004,"intra_dd":-26.3,"ret":-15.5},{"year":2005,"intra_dd":-9.2,"ret":-0.4},{"year":2006,"intra_dd":-4.3,"ret":21.3},{"year":2007,"intra_dd":-5.8,"ret":29.6},{"year":2008,"intra_dd":-36.2,"ret":-23.8},{"year":2009,"intra_dd":-17.5,"ret":28.5},{"year":2010,"intra_dd":-11.6,"ret":18.9},{"year":2011,"intra_dd":-9.1,"ret":10.4},{"year":2012,"intra_dd":-10.6,"ret":6.3},{"year":2013,"intra_dd":-12.8,"ret":13.0},{"year":2014,"intra_dd":-9.9,"ret":6.9},{"year":2015,"intra_dd":-11.8,"ret":5.3},{"year":2016,"intra_dd":-12.2,"ret":1.0},{"year":2017,"intra_dd":-4.2,"ret":13.5},{"year":2018,"intra_dd":-13.6,"ret":7.6},{"year":2019,"intra_dd":-10.2,"ret":21.7},{"year":2020,"intra_dd":-37.0,"ret":3.1},{"year":2021,"intra_dd":-8.7,"ret":15.8},{"year":2022,"intra_dd":-16.7,"ret":10.4},{"year":2023,"intra_dd":-17.3,"ret":-3.4},{"year":2024,"intra_dd":-14.9,"ret":7.3},{"year":2025,"intra_dd":-9.8,"ret":16.4},{"year":2026,"intra_dd":-7.9,"ret":22.4}]}